genshinhelper/__init__.py
genshinhelper/__main__.py
genshinhelper/__version__.py
genshinhelper/cloudgenshin.py
genshinhelper/config.py
genshinhelper/core.py
genshinhelper/exceptions.py
genshinhelper/hoyolab.py
genshinhelper/jfsc.py
genshinhelper/mihoyo.py
genshinhelper/utils.py
genshinhelper/weibo.py
genshinhelper/locale/en/LC_MESSAGES/genshinhelper.mo
genshinhelper/locale/zh/LC_MESSAGES/genshinhelper.mo
genshinhelper-2.1.3.data/data/genshinhelper/locale/en/LC_MESSAGES/genshinhelper.mo
genshinhelper-2.1.3.data/data/genshinhelper/locale/zh/LC_MESSAGES/genshinhelper.mo
genshinhelper-2.1.3.dist-info/LICENSE
genshinhelper-2.1.3.dist-info/METADATA
genshinhelper-2.1.3.dist-info/WHEEL
genshinhelper-2.1.3.dist-info/entry_points.txt
genshinhelper-2.1.3.dist-info/top_level.txt
genshinhelper-2.1.3.dist-info/RECORD
